pyconse24_demo-0.1.0.dist-info/METADATA
pyconse24_demo-0.1.0.dist-info/WHEEL
pyconse24_demo/__init__.py
pyconse24_demo-0.1.0.dist-info/RECORD
