Metadata-Version: 2.1
Name: pyconse24-demo
Version: 0.1.0
Summary: Sample project to download the weather forcast for Stockholm
Author-Email: Z <seal198321@gmail.com>
License: MIT
Requires-Python: >=3.11
Requires-Dist: httpx>=0.27.2
Requires-Dist: plotille>=5.0.0
